setup.cfg
setup.py
pypd/__init__.py
pypd/errors.py
pypd/log.py
pypd/mixins.py
pypd/version.py
pypd.egg-info/PKG-INFO
pypd.egg-info/SOURCES.txt
pypd.egg-info/dependency_links.txt
pypd.egg-info/requires.txt
pypd.egg-info/top_level.txt
pypd/models/__init__.py
pypd/models/ability.py
pypd/models/add_ons.py
pypd/models/alert.py
pypd/models/entity.py
pypd/models/escalation_policy.py
pypd/models/event.py
pypd/models/incident.py
pypd/models/integration.py
pypd/models/log_entry.py
pypd/models/maintenance_window.py
pypd/models/note.py
pypd/models/notification.py
pypd/models/on_call.py
pypd/models/schedule.py
pypd/models/service.py
pypd/models/team.py
pypd/models/user.py
pypd/models/vendor.py
test/__init__.py
test/runtests.py
test/unit/__init__.py
test/unit/clientmixin.py
test/unit/models/__init__.py
test/unit/models/alert.py
test/unit/models/entity.py
test/unit/models/escalation_policy.py
test/unit/models/incident.py
test/unit/models/integration.py