Metadata-Version: 1.1
Name: pypd
Version: 1.0.0
Summary: A python client for PagerDuty API
Home-page: https://github.com/PagerDuty/pagerduty-api-python-client
Author: JD Cumpson
Author-email: jdc@pagerduty.com
License: MIT
Download-URL: https://github.com/PagerDuty/pagerduty-api-python-client/archive/master.tar.gz
Platform: UNKNOWN
Classifier: Programming Language :: Python
Classifier: Programming Language :: Python :: 2
Classifier: Programming Language :: Python :: 3
Classifier: Topic :: Software Development
Classifier: Topic :: Software Development :: Libraries
Classifier: Topic :: Software Development :: Libraries :: Python Modules
